ambient_package_update/__init__.py
ambient_package_update/cli.py
ambient_package_update/metadata/__init__.py
ambient_package_update/metadata/author.py
ambient_package_update/metadata/constants.py
ambient_package_update/metadata/executables.py
ambient_package_update/metadata/maintainer.py
ambient_package_update/metadata/package.py
ambient_package_update/metadata/readme.py
ambient_package_update/metadata/ruff_ignored_inspection.py
ambient_package_update/templates/.editorconfig.tpl
ambient_package_update/templates/.gitignore.tpl
ambient_package_update/templates/.pre-commit-config.yaml.tpl
ambient_package_update/templates/.readthedocs.yaml.tpl
ambient_package_update/templates/CONTRIBUTING.md.tpl
ambient_package_update/templates/MANIFEST.in.tpl
ambient_package_update/templates/README.md.tpl
ambient_package_update/templates/SECURITY.md.tpl
ambient_package_update/templates/pyproject.toml.tpl
ambient_package_update/templates/.github/workflows/ci.yml.tpl
ambient_package_update/templates/docs/Makefile.tpl
ambient_package_update/templates/docs/conf.py.tpl
ambient_package_update/templates/docs/make.bat.tpl
ambient_package_update/templates/scripts/unix/install_requirements.sh.tpl
ambient_package_update/templates/scripts/unix/publish_to_pypi.sh.tpl
ambient_package_update/templates/scripts/windows/install_requirements.ps1.tpl
ambient_package_update/templates/scripts/windows/publish_to_pypi.ps1.tpl
ambient_package_update/templates/snippets/badges.tpl
ambient_package_update/templates/snippets/content.tpl
ambient_package_update/templates/snippets/empty.tpl
ambient_package_update/templates/snippets/installation.tpl
ambient_package_update/templates/snippets/links.tpl
ambient_package_update/templates/snippets/maintenance.tpl
ambient_package_update/templates/snippets/publish.tpl
ambient_package_update/templates/snippets/tagline.tpl
ambient_package_update/templates/snippets/licenses/GPL.md
ambient_package_update/templates/snippets/licenses/MIT.md
ambient_package_update-25.10.18.dist-info/METADATA
ambient_package_update-25.10.18.dist-info/WHEEL
ambient_package_update-25.10.18.dist-info/licenses/LICENSE.md
ambient_package_update-25.10.18.dist-info/RECORD
