Metadata-Version: 2.4
Name: ambient-package-update
Version: 25.10.18
Summary: Ambient package update tool for clean and swift maintenance
Project-URL: Homepage, https://github.com/ambient-innovation/ambient-package-update/
Project-URL: Documentation, https://github.com/ambient-innovation/ambient-package-update/blob/master/README.md
Project-URL: Maintained by, https://ambient.digital/
Project-URL: Bugtracker, https://github.com/ambient-innovation/ambient-package-update/issues
Project-URL: Changelog, https://github.com/ambient-innovation/ambient-package-update/blob/master/CHANGES.md
Author-email: Ambient Digital <hello@ambient.digital>
License: MIT License
License-File: LICENSE.md
Classifier: Development Status :: 5 - Production/Stable
Classifier: Environment :: Console
Classifier: Intended Audience :: Developers
Classifier: License :: OSI Approved :: MIT License
Classifier: Natural Language :: English
Classifier: Operating System :: OS Independent
Classifier: Programming Language :: Python
Classifier: Programming Language :: Python :: 3
Classifier: Programming Language :: Python :: 3.13
Classifier: Topic :: Utilities
Requires-Python: >=3.10
Requires-Dist: jinja2~=3.1
Requires-Dist: typer~=0.19
Requires-Dist: uv~=0.9
